dbnd_aws/__init__.py
dbnd_aws/_plugin.py
dbnd_aws/credentials.py
dbnd_aws/env.py
dbnd_aws/utils.py
dbnd_aws/batch/__init__.py
dbnd_aws/batch/aws_batch_ctrl.py
dbnd_aws/emr/__init__.py
dbnd_aws/emr/emr_cluster.py
dbnd_aws/emr/emr_cluster_builder.py
dbnd_aws/emr/emr_config.py
dbnd_aws/emr/emr_ctrl.py
dbnd_aws/emr/emr_step.py
dbnd_aws/fs/__init__.py
dbnd_aws/fs/s3.py
dbnd_aws/sagemaker/__init__.py
dbnd_aws/sagemaker/estimator_config.py
dbnd_aws/sagemaker/sagemaker_ctrl.py
dbnd_aws/sagemaker/sagemaker_task.py
dbnd_aws-1.0.30.1.dist-info/LICENSE
dbnd_aws-1.0.30.1.dist-info/METADATA
dbnd_aws-1.0.30.1.dist-info/WHEEL
dbnd_aws-1.0.30.1.dist-info/entry_points.txt
dbnd_aws-1.0.30.1.dist-info/top_level.txt
dbnd_aws-1.0.30.1.dist-info/RECORD
